f2/__init__.py
f2/app.py
f2/commands.py
f2/config.py
f2/debug.py
f2/errors.py
f2/keymap.py
f2/main.py
f2/shell.py
f2/update.py
f2/fs/arch.py
f2/fs/node.py
f2/fs/util.py
f2/tcss/main.tcss
f2/widgets/bookmarks.py
f2/widgets/config.py
f2/widgets/connect.py
f2/widgets/dialogs.py
f2/widgets/filelist.py
f2/widgets/form.py
f2/widgets/help.py
f2/widgets/panel.py
f2/widgets/preview.py
f2_commander-0.8.0.dist-info/licenses/LICENSE
f2_commander-0.8.0.dist-info/METADATA
f2_commander-0.8.0.dist-info/WHEEL
f2_commander-0.8.0.dist-info/entry_points.txt
f2_commander-0.8.0.dist-info/top_level.txt
f2_commander-0.8.0.dist-info/RECORD
