Metadata-Version: 2.4
Name: f2-commander
Version: 0.8.0
Summary: F2 Commander is an orthodox file manager for the modern world.
Author-email: Timur Rubeko <timcandid@gmail.com>
License-Expression: MPL-2.0
Project-URL: Homepage, https://candidtim.github.io/f2-commander
Project-URL: Repository, https://github.com/candidtim/f2-commander
Project-URL: Issues, https://github.com/candidtim/f2-commander/issues
Keywords: file,manager,commander
Classifier: Development Status :: 5 - Production/Stable
Classifier: Intended Audience :: End Users/Desktop
Classifier: Programming Language :: Python :: 3.10
Classifier: Programming Language :: Python :: 3.11
Classifier: Programming Language :: Python :: 3.12
Classifier: Programming Language :: Python :: 3.13
Classifier: Programming Language :: Python :: 3.14
Classifier: Operating System :: MacOS
Classifier: Operating System :: POSIX :: Linux
Classifier: Environment :: Console
Classifier: Topic :: Desktop Environment :: File Managers
Requires-Python: <3.15,>=3.10
License-File: LICENSE
Requires-Dist: textual<7,>=6.7.1
Requires-Dist: humanize<5,>=4.14.0
Requires-Dist: send2trash<2,>=1.8.3
Requires-Dist: platformdirs<5,>=4.5.1
Requires-Dist: fsspec>=2025.12.0
Requires-Dist: libarchive-c<6,>=5.3
Requires-Dist: pydantic<3,>=2.12.5
Requires-Dist: click<9,>=8.3.1
Requires-Dist: textual-image[textual]<1,>=0.8.4
Requires-Dist: pillow<13,>=12.0
Requires-Dist: pymupdf>=1.26.6
Dynamic: license-file
